{
    "id": "9eca50f832eda41f67946c09b42cbf15",
    "name": "Swagger Petstore",
    "description": null,
    "auth": null,
    "events": null,
    "variables": [],
    "order": [],
    "folders_order": [],
    "folders": [],
    "requests": [
        {
            "id": "62c7d96253855173b46b91a563acfb80",
            "name": "Add a new pet to the store",
            "url": "\/pet",
            "description": "",
            "data": [],
            "dataMode": "raw",
            "headerData": null,
            "method": "post",
            "pathVariableData": [],
            "queryParams": [],
            "auth": null,
            "events": null,
            "folder": null,
            "protocolProfileBehavior": {
                "disableBodyPruning": true
            },
            "responses": [],
            "currentHelper": null,
            "helperAttributes": null,
            "collectionId": "9eca50f832eda41f67946c09b42cbf15",
            "rawModeData": ""
        },
        {
            "id": "73aac23245a4fbd47756c364315267fb",
            "name": "Update an existing pet",
            "url": "\/pet",
            "description": "",
            "data": [],
            "dataMode": "raw",
            "headerData": null,
            "method": "put",
            "pathVariableData": [],
            "queryParams": [],
            "auth": null,
            "events": null,
            "folder": null,
            "protocolProfileBehavior": {
                "disableBodyPruning": true
            },
            "responses": [],
            "currentHelper": null,
            "helperAttributes": null,
            "collectionId": "9eca50f832eda41f67946c09b42cbf15",
            "rawModeData": ""
        },
        {
            "id": "7f13fb556f922431196e4a861179c6b7",
            "name": "Finds Pets by status",
            "url": "\/pet\/findByStatus",
            "description": "Multiple status values can be provided with comma separated strings",
            "data": [],
            "dataMode": "raw",
            "headerData": null,
            "method": "get",
            "pathVariableData": [],
            "queryParams": [
                {
                    "key": "status",
                    "description": "Status values that need to be considered for filter",
                    "value": "",
                    "equals": true,
                    "enabled": true
                }
            ],
            "auth": null,
            "events": null,
            "folder": null,
            "protocolProfileBehavior": {
                "disableBodyPruning": true
            },
            "responses": [],
            "currentHelper": null,
            "helperAttributes": null,
            "collectionId": "9eca50f832eda41f67946c09b42cbf15",
            "rawModeData": ""
        },
        {
            "id": "5a7c7bc3336e8ae6026f9cc70cee21be",
            "name": "Finds Pets by tags",
            "url": "\/pet\/findByTags",
            "description": "Muliple tags can be provided with comma separated strings. Use tag1, tag2, tag3 for testing.",
            "data": [],
            "dataMode": "raw",
            "headerData": null,
            "method": "get",
            "pathVariableData": [],
            "queryParams": [
                {
                    "key": "tags",
                    "description": "Tags to filter by",
                    "value": "",
                    "equals": true,
                    "enabled": true
                }
            ],
            "auth": null,
            "events": null,
            "folder": null,
            "protocolProfileBehavior": {
                "disableBodyPruning": true
            },
            "responses": [],
            "currentHelper": null,
            "helperAttributes": null,
            "collectionId": "9eca50f832eda41f67946c09b42cbf15",
            "rawModeData": ""
        },
        {
            "id": "031b6801fc00371bb8f7d5db703f825d",
            "name": "Find pet by ID",
            "url": "\/pet\/{petId}",
            "description": "Returns a single pet",
            "data": [],
            "dataMode": "raw",
            "headerData": null,
            "method": "get",
            "pathVariableData": [],
            "queryParams": [
                {
                    "key": "petId",
                    "description": "ID of pet to return",
                    "value": "",
                    "equals": true,
                    "enabled": true
                }
            ],
            "auth": null,
            "events": null,
            "folder": null,
            "protocolProfileBehavior": {
                "disableBodyPruning": true
            },
            "responses": [],
            "currentHelper": null,
            "helperAttributes": null,
            "collectionId": "9eca50f832eda41f67946c09b42cbf15",
            "rawModeData": ""
        },
        {
            "id": "090e2704bdbeaec7f880fd821aad09fa",
            "name": "Updates a pet in the store with form data",
            "url": "\/pet\/{petId}",
            "description": "",
            "data": [],
            "dataMode": "raw",
            "headerData": null,
            "method": "post",
            "pathVariableData": [],
            "queryParams": [
                {
                    "key": "petId",
                    "description": "ID of pet to return",
                    "value": "",
                    "equals": true,
                    "enabled": true
                },
                {
                    "key": "name",
                    "description": "Updated name of the pet",
                    "value": "",
                    "equals": true,
                    "enabled": true
                },
                {
                    "key": "status",
                    "description": "Updated status of the pet",
                    "value": "",
                    "equals": true,
                    "enabled": true
                }
            ],
            "auth": null,
            "events": null,
            "folder": null,
            "protocolProfileBehavior": {
                "disableBodyPruning": true
            },
            "responses": [],
            "currentHelper": null,
            "helperAttributes": null,
            "collectionId": "9eca50f832eda41f67946c09b42cbf15",
            "rawModeData": ""
        },
        {
            "id": "f0693ae4f944ea492ef76e2cd1e2f5fc",
            "name": "Deletes a pet",
            "url": "\/pet\/{petId}",
            "description": "",
            "data": [],
            "dataMode": "raw",
            "headerData": null,
            "method": "delete",
            "pathVariableData": [],
            "queryParams": [
                {
                    "key": "petId",
                    "description": "ID of pet to return",
                    "value": "",
                    "equals": true,
                    "enabled": true
                }
            ],
            "auth": null,
            "events": null,
            "folder": null,
            "protocolProfileBehavior": {
                "disableBodyPruning": true
            },
            "responses": [],
            "currentHelper": null,
            "helperAttributes": null,
            "collectionId": "9eca50f832eda41f67946c09b42cbf15",
            "rawModeData": ""
        },
        {
            "id": "0ad22801142b0090e692127367bf056e",
            "name": "uploads an image",
            "url": "\/pet\/{petId}\/uploadImage",
            "description": "",
            "data": [],
            "dataMode": "raw",
            "headerData": null,
            "method": "post",
            "pathVariableData": [],
            "queryParams": [
                {
                    "key": "petId",
                    "description": "ID of pet to return",
                    "value": "",
                    "equals": true,
                    "enabled": true
                },
                {
                    "key": "additionalMetadata",
                    "description": "Additional data to pass to server",
                    "value": "",
                    "equals": true,
                    "enabled": true
                },
                {
                    "key": "file",
                    "description": "file to upload",
                    "value": "",
                    "equals": true,
                    "enabled": true
                }
            ],
            "auth": null,
            "events": null,
            "folder": null,
            "protocolProfileBehavior": {
                "disableBodyPruning": true
            },
            "responses": [],
            "currentHelper": null,
            "helperAttributes": null,
            "collectionId": "9eca50f832eda41f67946c09b42cbf15",
            "rawModeData": ""
        },
        {
            "id": "c5f63a990fbe6004b42e56bdf69fce02",
            "name": "Returns pet inventories by status",
            "url": "\/store\/inventory",
            "description": "Returns a map of status codes to quantities",
            "data": [],
            "dataMode": "raw",
            "headerData": null,
            "method": "get",
            "pathVariableData": [],
            "queryParams": [],
            "auth": null,
            "events": null,
            "folder": null,
            "protocolProfileBehavior": {
                "disableBodyPruning": true
            },
            "responses": [],
            "currentHelper": null,
            "helperAttributes": null,
            "collectionId": "9eca50f832eda41f67946c09b42cbf15",
            "rawModeData": ""
        },
        {
            "id": "9f9307045d91399ade22d4cd8f401e79",
            "name": "Place an order for a pet",
            "url": "\/store\/order",
            "description": "",
            "data": [],
            "dataMode": "raw",
            "headerData": null,
            "method": "post",
            "pathVariableData": [],
            "queryParams": [],
            "auth": null,
            "events": null,
            "folder": null,
            "protocolProfileBehavior": {
                "disableBodyPruning": true
            },
            "responses": [],
            "currentHelper": null,
            "helperAttributes": null,
            "collectionId": "9eca50f832eda41f67946c09b42cbf15",
            "rawModeData": ""
        },
        {
            "id": "a731c238705c2d15b7019a73b4025c27",
            "name": "Find purchase order by ID",
            "url": "\/store\/order\/{orderId}",
            "description": "For valid response try integer IDs with value >= 1 and <= 10. Other values will generated exceptions",
            "data": [],
            "dataMode": "raw",
            "headerData": null,
            "method": "get",
            "pathVariableData": [],
            "queryParams": [
                {
                    "key": "orderId",
                    "description": "ID of pet that needs to be fetched",
                    "value": "",
                    "equals": true,
                    "enabled": true
                }
            ],
            "auth": null,
            "events": null,
            "folder": null,
            "protocolProfileBehavior": {
                "disableBodyPruning": true
            },
            "responses": [],
            "currentHelper": null,
            "helperAttributes": null,
            "collectionId": "9eca50f832eda41f67946c09b42cbf15",
            "rawModeData": ""
        },
        {
            "id": "43674e7bfcb262882896dbf7aadc2894",
            "name": "Delete purchase order by ID",
            "url": "\/store\/order\/{orderId}",
            "description": "For valid response try integer IDs with positive integer value. Negative or non-integer values will generate API errors",
            "data": [],
            "dataMode": "raw",
            "headerData": null,
            "method": "delete",
            "pathVariableData": [],
            "queryParams": [
                {
                    "key": "orderId",
                    "description": "ID of pet that needs to be fetched",
                    "value": "",
                    "equals": true,
                    "enabled": true
                }
            ],
            "auth": null,
            "events": null,
            "folder": null,
            "protocolProfileBehavior": {
                "disableBodyPruning": true
            },
            "responses": [],
            "currentHelper": null,
            "helperAttributes": null,
            "collectionId": "9eca50f832eda41f67946c09b42cbf15",
            "rawModeData": ""
        },
        {
            "id": "d29086200056fe5eaa2bb22ecbb78441",
            "name": "Create user",
            "url": "\/user",
            "description": "This can only be done by the logged in user.",
            "data": [],
            "dataMode": "raw",
            "headerData": null,
            "method": "post",
            "pathVariableData": [],
            "queryParams": [],
            "auth": null,
            "events": null,
            "folder": null,
            "protocolProfileBehavior": {
                "disableBodyPruning": true
            },
            "responses": [],
            "currentHelper": null,
            "helperAttributes": null,
            "collectionId": "9eca50f832eda41f67946c09b42cbf15",
            "rawModeData": ""
        },
        {
            "id": "5979e18d440bea5607560026a3988388",
            "name": "Creates list of users with given input array",
            "url": "\/user\/createWithArray",
            "description": "",
            "data": [],
            "dataMode": "raw",
            "headerData": null,
            "method": "post",
            "pathVariableData": [],
            "queryParams": [],
            "auth": null,
            "events": null,
            "folder": null,
            "protocolProfileBehavior": {
                "disableBodyPruning": true
            },
            "responses": [],
            "currentHelper": null,
            "helperAttributes": null,
            "collectionId": "9eca50f832eda41f67946c09b42cbf15",
            "rawModeData": ""
        },
        {
            "id": "fac380a8c1fffdfce6ef6b9a7cb00196",
            "name": "Creates list of users with given input array",
            "url": "\/user\/createWithList",
            "description": "",
            "data": [],
            "dataMode": "raw",
            "headerData": null,
            "method": "post",
            "pathVariableData": [],
            "queryParams": [],
            "auth": null,
            "events": null,
            "folder": null,
            "protocolProfileBehavior": {
                "disableBodyPruning": true
            },
            "responses": [],
            "currentHelper": null,
            "helperAttributes": null,
            "collectionId": "9eca50f832eda41f67946c09b42cbf15",
            "rawModeData": ""
        },
        {
            "id": "15ce4f19df9c31b540fe44b4e7f9ff63",
            "name": "Logs user into the system",
            "url": "\/user\/login",
            "description": "",
            "data": [],
            "dataMode": "raw",
            "headerData": null,
            "method": "get",
            "pathVariableData": [],
            "queryParams": [
                {
                    "key": "username",
                    "description": "The user name for login",
                    "value": "",
                    "equals": true,
                    "enabled": true
                },
                {
                    "key": "password",
                    "description": "The password for login in clear text",
                    "value": "",
                    "equals": true,
                    "enabled": true
                }
            ],
            "auth": null,
            "events": null,
            "folder": null,
            "protocolProfileBehavior": {
                "disableBodyPruning": true
            },
            "responses": [],
            "currentHelper": null,
            "helperAttributes": null,
            "collectionId": "9eca50f832eda41f67946c09b42cbf15",
            "rawModeData": ""
        },
        {
            "id": "62754bb8bfb3509b6174aa169c61783f",
            "name": "Logs out current logged in user session",
            "url": "\/user\/logout",
            "description": "",
            "data": [],
            "dataMode": "raw",
            "headerData": null,
            "method": "get",
            "pathVariableData": [],
            "queryParams": [],
            "auth": null,
            "events": null,
            "folder": null,
            "protocolProfileBehavior": {
                "disableBodyPruning": true
            },
            "responses": [],
            "currentHelper": null,
            "helperAttributes": null,
            "collectionId": "9eca50f832eda41f67946c09b42cbf15",
            "rawModeData": ""
        },
        {
            "id": "5dcd4f45ccb09ed88e9575b487bf6b3b",
            "name": "Get user by user name",
            "url": "\/user\/{username}",
            "description": "",
            "data": [],
            "dataMode": "raw",
            "headerData": null,
            "method": "get",
            "pathVariableData": [],
            "queryParams": [
                {
                    "key": "username",
                    "description": "The name that needs to be fetched. Use user1 for testing. ",
                    "value": "",
                    "equals": true,
                    "enabled": true
                }
            ],
            "auth": null,
            "events": null,
            "folder": null,
            "protocolProfileBehavior": {
                "disableBodyPruning": true
            },
            "responses": [],
            "currentHelper": null,
            "helperAttributes": null,
            "collectionId": "9eca50f832eda41f67946c09b42cbf15",
            "rawModeData": ""
        },
        {
            "id": "ebb8602854aa9f757504a610532407a9",
            "name": "Updated user",
            "url": "\/user\/{username}",
            "description": "This can only be done by the logged in user.",
            "data": [],
            "dataMode": "raw",
            "headerData": null,
            "method": "put",
            "pathVariableData": [],
            "queryParams": [
                {
                    "key": "username",
                    "description": "The name that needs to be fetched. Use user1 for testing. ",
                    "value": "",
                    "equals": true,
                    "enabled": true
                }
            ],
            "auth": null,
            "events": null,
            "folder": null,
            "protocolProfileBehavior": {
                "disableBodyPruning": true
            },
            "responses": [],
            "currentHelper": null,
            "helperAttributes": null,
            "collectionId": "9eca50f832eda41f67946c09b42cbf15",
            "rawModeData": ""
        },
        {
            "id": "77e14365ff7e83235e765e61f04f38de",
            "name": "Delete user",
            "url": "\/user\/{username}",
            "description": "This can only be done by the logged in user.",
            "data": [],
            "dataMode": "raw",
            "headerData": null,
            "method": "delete",
            "pathVariableData": [],
            "queryParams": [
                {
                    "key": "username",
                    "description": "The name that needs to be fetched. Use user1 for testing. ",
                    "value": "",
                    "equals": true,
                    "enabled": true
                }
            ],
            "auth": null,
            "events": null,
            "folder": null,
            "protocolProfileBehavior": {
                "disableBodyPruning": true
            },
            "responses": [],
            "currentHelper": null,
            "helperAttributes": null,
            "collectionId": "9eca50f832eda41f67946c09b42cbf15",
            "rawModeData": ""
        }
    ]
}